geospock_cli/__init__.py
geospock_cli/config_reader.py
geospock_cli/exceptions.py
geospock_cli/full_help_command.py
geospock_cli/geospockcli.py
geospock_cli/message_sender.py
geospock_cli/output.py
geospock_cli/constants/__init__.py
geospock_cli/constants/defaults.py
geospock_cli/constants/envvars.py
geospock_cli/constants/help.py
geospock_cli/constants/messages.py
geospock_cli/group_commands/__init__.py
geospock_cli/group_commands/group_commands.py
geospock_cli/group_commands/group_permission_commands.py
geospock_cli/permission_utils/__init__.py
geospock_cli/permission_utils/permission_request.py
geospock_cli/permission_utils/permission_utils.py
geospock_cli/schema_commands/__init__.py
geospock_cli/schema_commands/schema_commands.py
geospock_cli/schema_commands/schema_permission_commands.py
geospock_cli/table_commands/__init__.py
geospock_cli/table_commands/table_commands.py
geospock_cli/table_commands/table_permission_commands.py
test/__init__.py
test/test_gsdb_cli_group.py
test/test_gsdb_cli_schema.py
test/test_gsdb_cli_table.py
gsdb_cli-0.0.24.dist-info/LICENSE
gsdb_cli-0.0.24.dist-info/METADATA
gsdb_cli-0.0.24.dist-info/WHEEL
gsdb_cli-0.0.24.dist-info/entry_points.txt
gsdb_cli-0.0.24.dist-info/top_level.txt
gsdb_cli-0.0.24.dist-info/RECORD
