Metadata-Version: 2.1
Name: gsdb-cli
Version: 0.0.24
Summary: GeoSpock DB CLI
Home-page: http://geospock.com/
Author: GeoSpock Ltd
Author-email: cli-development@geospock.com
License: MIT
Platform: UNKNOWN
Classifier: Development Status :: 3 - Alpha
Classifier: Environment :: Console
Classifier: License :: OSI Approved :: MIT License
Classifier: Programming Language :: Python :: 3
Requires-Python: >=3.5
Requires-Dist: Click
Requires-Dist: boto3
Requires-Dist: keyring
Requires-Dist: requests
Requires-Dist: tenacity
Requires-Dist: urllib3
